AUTHORS
INSTALL
LICENSE
MANIFEST.in
README.rst
setup.py
django_rforum.egg-info/PKG-INFO
django_rforum.egg-info/SOURCES.txt
django_rforum.egg-info/dependency_links.txt
django_rforum.egg-info/not-zip-safe
django_rforum.egg-info/requires.txt
django_rforum.egg-info/top_level.txt
docs/Makefile
docs/source/conf.py
docs/source/index.rst
rforum/__init__.py
rforum/admin.py
rforum/forms.py
rforum/middleware.py
rforum/models.py
rforum/signals.py
rforum/tests.py
rforum/urls.py
rforum/utils.py
rforum/views.py
rforum/migrations/0001_initial.py
rforum/migrations/0002_auto__del_field_topic_status.py
rforum/migrations/0003_auto__add_field_topic_status.py
rforum/migrations/0004_auto__del_userprofile__add_log.py
rforum/migrations/0005_auto__add_field_forum_parent.py
rforum/migrations/__init__.py
rforum/rforum-example/manage.py
rforum/rforum-example/project/__init__.py
rforum/rforum-example/project/context_processors.py
rforum/rforum-example/project/settings.py
rforum/rforum-example/project/urls.py
rforum/rforum-example/project/wsgi.py
rforum/rforum-example/project/db/delete.me
rforum/rforum-example/project/media/uploads/delete.me
rforum/rforum-example/project/static/css/PIE.htc
rforum/rforum-example/project/static/css/bootstrap-responsive.css
rforum/rforum-example/project/static/css/bootstrap-responsive.min.css
rforum/rforum-example/project/static/css/bootstrap.css
rforum/rforum-example/project/static/css/bootstrap.min.css
rforum/rforum-example/project/static/css/colorbox.css
rforum/rforum-example/project/static/css/custom.css
rforum/rforum-example/project/static/css/fonts/Calluna-Regular.otf
rforum/rforum-example/project/static/filebrowser/css/filebrowser.css
rforum/rforum-example/project/static/filebrowser/css/filebrowser.css.rej
rforum/rforum-example/project/static/filebrowser/img/filebrowser_icon_delete.gif
rforum/rforum-example/project/static/filebrowser/img/filebrowser_icon_delete_hover.gif
rforum/rforum-example/project/static/filebrowser/img/filebrowser_icon_rename.gif
rforum/rforum-example/project/static/filebrowser/img/filebrowser_icon_rename_hover.gif
rforum/rforum-example/project/static/filebrowser/img/filebrowser_icon_select.gif
