Metadata-Version: 1.1
Name: django-rforum
Version: 0.0.24
Summary: Yet another Django Forum App
Home-page: http://bitbucket.org/r0sk/django-rforum
Author: Oscar M. Lage Guitian
Author-email: im@oscarmlage.com
License: BSD licence, see LICENSE file
Keywords: django application forum board
Platform: UNKNOWN
Classifier: Development Status :: 4 - Beta
Classifier: Environment :: Web Environment
Classifier: Framework :: Django
Classifier: Intended Audience :: Developers
Classifier: License :: OSI Approved :: BSD License
Classifier: Operating System :: OS Independent
Classifier: Programming Language :: Python
Classifier: Topic :: Internet :: WWW/HTTP :: Dynamic Content :: Message Boards
Classifier: Topic :: Software Development :: Libraries :: Python Modules
